{"cameraMode":{"drawMode":0,"name":"Shaded","section":"Shading Mode"},"sceneLighting":true,"audioPlay":false,"sceneViewState":{"m_AlwaysRefresh":false,"showFog":true,"showSkybox":true,"showFlares":true,"showImageEffects":true,"showParticleSystems":true,"showVisualEffectGraphs":true,"m_FxEnabled":true},"in2DMode":false,"pivot":{"x":-31.736148834228517,"y":5.98445987701416,"z":18.074371337890626},"rotation":{"x":-0.04778255149722099,"y":-0.9479100704193115,"z":0.26391956210136416,"w":-0.1726026087999344},"size":7.658141613006592,"orthographic":false}